Metadata-Version: 2.1
Name: wifi-qrcode
Version: 2.1.0
Summary: Generate WiFi Access QR Codes
Home-page: https://github.com/shpaker/wifi_qrcode
Author: Aleksandr Shpak
Author-email: shpaker@gmail.com
License: UNKNOWN
Platform: UNKNOWN
Classifier: Programming Language :: Python :: 3
Classifier: License :: OSI Approved :: MIT License
Classifier: Operating System :: OS Independent
Classifier: Topic :: Communications
